text_chaos/__init__.py
text_chaos/emoji_data.py
text_chaos/pirate_data.py
text_chaos/shakespeare_data.py
text_chaos/transformers.py
text_chaos/yoda_transformer.py
text_chaos-1.0.2.dist-info/METADATA
text_chaos-1.0.2.dist-info/WHEEL
text_chaos-1.0.2.dist-info/licenses/LICENSE
text_chaos-1.0.2.dist-info/RECORD
