Metadata-Version: 2.4
Name: text-chaos
Version: 1.0.2
Summary: A fun library for playful string manipulations like leetify, uwuify, zalgo, and more!
Project-URL: Homepage, https://github.com/guroosh/text-chaos
Project-URL: Documentation, https://github.com/guroosh/text-chaos#readme
Project-URL: Repository, https://github.com/guroosh/text-chaos.git
Project-URL: Issues, https://github.com/guroosh/text-chaos/issues
Author-email: Guroosh <guroosh.07@gmail.com>
Maintainer-email: Guroosh <guroosh.07@gmail.com>
License: MIT License
License-File: LICENSE
Keywords: fun,leet,manipulation,string,text,transformation,uwu
Classifier: Development Status :: 4 - Beta
Classifier: Intended Audience :: Developers
Classifier: License :: OSI Approved :: MIT License
Classifier: Operating System :: OS Independent
Classifier: Programming Language :: Python :: 3
Classifier: Programming Language :: Python :: 3.8
Classifier: Programming Language :: Python :: 3.9
Classifier: Programming Language :: Python :: 3.10
Classifier: Programming Language :: Python :: 3.11
Classifier: Programming Language :: Python :: 3.12
Classifier: Topic :: Software Development :: Libraries :: Python Modules
Classifier: Topic :: Text Processing
Requires-Python: >=3.8
Provides-Extra: dev
Requires-Dist: black>=22.0.0; extra == 'dev'
Requires-Dist: isort>=5.0.0; extra == 'dev'
Requires-Dist: pytest-cov>=4.0.0; extra == 'dev'
Requires-Dist: pytest>=7.0.0; extra == 'dev'
